wtforms_appengine/__init__.py
wtforms_appengine/db.py
wtforms_appengine/fields.py
wtforms_appengine/ndb.py
WTForms_Appengine-0.1.dist-info/DESCRIPTION.rst
WTForms_Appengine-0.1.dist-info/METADATA
WTForms_Appengine-0.1.dist-info/pydist.json
WTForms_Appengine-0.1.dist-info/RECORD
WTForms_Appengine-0.1.dist-info/top_level.txt
WTForms_Appengine-0.1.dist-info/WHEEL
